{"endInit":1476361895021,"executions":[{"result":{"type":"test","success":true},"startDate":1476361895021,"locations":[{"sourceEnd":3127,"executionCount":0,"line":88,"class":"org.apache.commons.math.analysis.solvers.BisectionSolver","sourceStart":3127},{"sourceEnd":3157,"executionCount":0,"line":89,"class":"org.apache.commons.math.analysis.solvers.BisectionSolver","sourceStart":3157}],"test":{"name":"testMath369","class":"org.apache.commons.math.analysis.solvers.BisectionSolverTest"},"decisions":[{"nbUse":44,"location":{"sourceEnd":3127,"line":88,"class":"org.apache.commons.math.analysis.solvers.BisectionSolver","sourceStart":3127},"value":{"instanceType":"New","class":"org.apache.commons.math.analysis.SinFunction"},"epsilon":0,"strategy":"Strat2A","used":true,"decisionType":"NEW"},{"nbUse":18,"location":{"sourceEnd":3157,"line":89,"class":"org.apache.commons.math.analysis.solvers.BisectionSolver","sourceStart":3157},"value":{"instanceType":"New","class":"org.apache.commons.math.analysis.SinFunction"},"epsilon":0,"strategy":"Strat2A","used":true,"decisionType":"NEW"}],"endDate":1476361895039,"metadata":{"seed":10,"strategy_selection":"exploration"}},{"result":{"error":"testMath369(org.apache.commons.math.analysis.solvers.BisectionSolverTest): null\nclass java.lang.NullPointerException: null\n    at org.apache.commons.math.analysis.solvers.BisectionSolver.solve(BisectionSolver.java:101)\n    at org.apache.commons.math.analysis.solvers.BisectionSolver.solve(BisectionSolver.java:56)\n    at org.apache.commons.math.analysis.solvers.BisectionSolver.solve(BisectionSolver.java:72)\n    at org.apache.commons.math.analysis.solvers.BisectionSolverTest.testMath369(BisectionSolverTest.java:21)\n    at sun.reflect.NativeMethodAccessorImpl.invoke0(NativeMethodAccessorImpl.java:-2)\n    at sun.reflect.NativeMethodAccessorImpl.invoke(NativeMethodAccessorImpl.java:57)\n    at sun.reflect.DelegatingMethodAccessorImpl.invoke(DelegatingMethodAccessorImpl.java:43)\n    at java.lang.reflect.Method.invoke(Method.java:606)\n    at junit.framework.TestCase.runTest(TestCase.java:176)\n    at junit.framework.TestCase.runBare(TestCase.java:141)\n    at junit.framework.TestResult$1.protect(TestResult.java:122)\n    at junit.framework.TestResult.runProtected(TestResult.java:142)\n    at junit.framework.TestResult.run(TestResult.java:125)\n    at junit.framework.TestCase.run(TestCase.java:129)\n    at junit.framework.TestSuite.runTest(TestSuite.java:255)\n    at junit.framework.TestSuite.run(TestSuite.java:250)\n    at org.junit.internal.runners.JUnit38ClassRunner.run(JUnit38ClassRunner.java:84)\n    at org.junit.runner.JUnitCore.run(JUnitCore.java:160)\n    at org.junit.runner.JUnitCore.run(JUnitCore.java:138)\n    at utils.sacha.runner.main.TestRunner.run(TestRunner.java:70)\n    at fr.inria.spirals.npefix.main.all.Launcher.run(Launcher.java:252)\n    at fr.inria.spirals.npefix.AbstractEvaluation.multipleRunsProject(AbstractEvaluation.java:77)\n    at fr.inria.spirals.npefix.resi.selector.AbstractSelectorEvaluation.runProject(AbstractSelectorEvaluation.java:35)\n    at fr.inria.spirals.npefix.resi.AbstractNPEDataset.math369(AbstractNPEDataset.java:193)\n    at sun.reflect.NativeMethodAccessorImpl.invoke0(NativeMethodAccessorImpl.java:-2)\n\n\n","type":"test","success":false},"startDate":1476361895039,"locations":[{"sourceEnd":3127,"executionCount":0,"line":88,"class":"org.apache.commons.math.analysis.solvers.BisectionSolver","sourceStart":3127}],"test":{"name":"testMath369","class":"org.apache.commons.math.analysis.solvers.BisectionSolverTest"},"decisions":[{"nbUse":44,"location":{"sourceEnd":3127,"line":88,"class":"org.apache.commons.math.analysis.solvers.BisectionSolver","sourceStart":3127},"value":{"instanceType":"New","class":"org.apache.commons.math.analysis.SinFunction"},"epsilon":0,"strategy":"Strat2A","used":true,"decisionType":"NEW"},{"nbUse":0,"location":{"sourceEnd":3157,"line":89,"class":"org.apache.commons.math.analysis.solvers.BisectionSolver","sourceStart":3157},"value":{"instanceType":"New","class":"org.apache.commons.math.analysis.SinFunction"},"epsilon":0,"strategy":"Strat2B","used":true,"decisionType":"NEW"}],"endDate":1476361895050,"metadata":{"seed":10,"strategy_selection":"exploration"}},{"result":{"type":"test","success":true},"startDate":1476361895051,"locations":[{"sourceEnd":3127,"executionCount":0,"line":88,"class":"org.apache.commons.math.analysis.solvers.BisectionSolver","sourceStart":3127},{"sourceEnd":3157,"executionCount":0,"line":89,"class":"org.apache.commons.math.analysis.solvers.BisectionSolver","sourceStart":3157}],"test":{"name":"testMath369","class":"org.apache.commons.math.analysis.solvers.BisectionSolverTest"},"decisions":[{"nbUse":44,"location":{"sourceEnd":3127,"line":88,"class":"org.apache.commons.math.analysis.solvers.BisectionSolver","sourceStart":3127},"value":{"instanceType":"New","class":"org.apache.commons.math.analysis.SinFunction"},"epsilon":0,"strategy":"Strat2A","used":true,"decisionType":"NEW"},{"nbUse":18,"location":{"sourceEnd":3157,"line":89,"class":"org.apache.commons.math.analysis.solvers.BisectionSolver","sourceStart":3157},"value":{"instanceType":"Primitive","value":false,"class":"class java.lang.Boolean"},"epsilon":0,"strategy":"Strat3","used":true,"decisionType":"NEW"}],"endDate":1476361895067,"metadata":{"seed":10,"strategy_selection":"exploration"}},{"result":{"type":"test","success":true},"startDate":1476361895067,"locations":[{"sourceEnd":3127,"executionCount":0,"line":88,"class":"org.apache.commons.math.analysis.solvers.BisectionSolver","sourceStart":3127},{"sourceEnd":3157,"executionCount":0,"line":89,"class":"org.apache.commons.math.analysis.solvers.BisectionSolver","sourceStart":3157}],"test":{"name":"testMath369","class":"org.apache.commons.math.analysis.solvers.BisectionSolverTest"},"decisions":[{"nbUse":44,"location":{"sourceEnd":3127,"line":88,"class":"org.apache.commons.math.analysis.solvers.BisectionSolver","sourceStart":3127},"value":{"instanceType":"New","class":"org.apache.commons.math.analysis.SinFunction"},"epsilon":0,"strategy":"Strat2A","used":true,"decisionType":"NEW"},{"nbUse":1,"location":{"sourceEnd":3157,"line":89,"class":"org.apache.commons.math.analysis.solvers.BisectionSolver","sourceStart":3157},"value":{"instanceType":"Variable","variableName":"min"},"epsilon":0,"strategy":"Strat4 VAR","used":true,"decisionType":"NEW"}],"endDate":1476361895078,"metadata":{"seed":10,"strategy_selection":"exploration"}},{"result":{"type":"test","success":true},"startDate":1476361895078,"locations":[{"sourceEnd":3127,"executionCount":0,"line":88,"class":"org.apache.commons.math.analysis.solvers.BisectionSolver","sourceStart":3127},{"sourceEnd":3157,"executionCount":0,"line":89,"class":"org.apache.commons.math.analysis.solvers.BisectionSolver","sourceStart":3157}],"test":{"name":"testMath369","class":"org.apache.commons.math.analysis.solvers.BisectionSolverTest"},"decisions":[{"nbUse":44,"location":{"sourceEnd":3127,"line":88,"class":"org.apache.commons.math.analysis.solvers.BisectionSolver","sourceStart":3127},"value":{"instanceType":"New","class":"org.apache.commons.math.analysis.SinFunction"},"epsilon":0,"strategy":"Strat2A","used":true,"decisionType":"NEW"},{"nbUse":1,"location":{"sourceEnd":3157,"line":89,"class":"org.apache.commons.math.analysis.solvers.BisectionSolver","sourceStart":3157},"value":{"instanceType":"Variable","variableName":"max"},"epsilon":0,"strategy":"Strat4 VAR","used":true,"decisionType":"NEW"}],"endDate":1476361895091,"metadata":{"seed":10,"strategy_selection":"exploration"}},{"result":{"type":"test","success":true},"startDate":1476361895091,"locations":[{"sourceEnd":3127,"executionCount":0,"line":88,"class":"org.apache.commons.math.analysis.solvers.BisectionSolver","sourceStart":3127},{"sourceEnd":3157,"executionCount":0,"line":89,"class":"org.apache.commons.math.analysis.solvers.BisectionSolver","sourceStart":3157}],"test":{"name":"testMath369","class":"org.apache.commons.math.analysis.solvers.BisectionSolverTest"},"decisions":[{"nbUse":44,"location":{"sourceEnd":3127,"line":88,"class":"org.apache.commons.math.analysis.solvers.BisectionSolver","sourceStart":3127},"value":{"instanceType":"New","class":"org.apache.commons.math.analysis.SinFunction"},"epsilon":0,"strategy":"Strat2A","used":true,"decisionType":"NEW"},{"nbUse":1,"location":{"sourceEnd":3157,"line":89,"class":"org.apache.commons.math.analysis.solvers.BisectionSolver","sourceStart":3157},"value":{"instanceType":"Variable","variableName":"fmin"},"epsilon":0,"strategy":"Strat4 VAR","used":true,"decisionType":"NEW"}],"endDate":1476361895103,"metadata":{"seed":10,"strategy_selection":"exploration"}},{"result":{"type":"test","success":true},"startDate":1476361895103,"locations":[{"sourceEnd":3127,"executionCount":0,"line":88,"class":"org.apache.commons.math.analysis.solvers.BisectionSolver","sourceStart":3127},{"sourceEnd":3157,"executionCount":0,"line":89,"class":"org.apache.commons.math.analysis.solvers.BisectionSolver","sourceStart":3157}],"test":{"name":"testMath369","class":"org.apache.commons.math.analysis.solvers.BisectionSolverTest"},"decisions":[{"nbUse":44,"location":{"sourceEnd":3127,"line":88,"class":"org.apache.commons.math.analysis.solvers.BisectionSolver","sourceStart":3127},"value":{"instanceType":"New","class":"org.apache.commons.math.analysis.SinFunction"},"epsilon":0,"strategy":"Strat2A","used":true,"decisionType":"NEW"},{"nbUse":1,"location":{"sourceEnd":3157,"line":89,"class":"org.apache.commons.math.analysis.solvers.BisectionSolver","sourceStart":3157},"value":{"instanceType":"Variable","variableName":"m"},"epsilon":0,"strategy":"Strat4 VAR","used":true,"decisionType":"NEW"}],"endDate":1476361895114,"metadata":{"seed":10,"strategy_selection":"exploration"}},{"result":{"type":"test","success":true},"startDate":1476361895114,"locations":[{"sourceEnd":3127,"executionCount":0,"line":88,"class":"org.apache.commons.math.analysis.solvers.BisectionSolver","sourceStart":3127},{"sourceEnd":3157,"executionCount":0,"line":89,"class":"org.apache.commons.math.analysis.solvers.BisectionSolver","sourceStart":3157}],"test":{"name":"testMath369","class":"org.apache.commons.math.analysis.solvers.BisectionSolverTest"},"decisions":[{"nbUse":44,"location":{"sourceEnd":3127,"line":88,"class":"org.apache.commons.math.analysis.solvers.BisectionSolver","sourceStart":3127},"value":{"instanceType":"New","class":"org.apache.commons.math.analysis.SinFunction"},"epsilon":0,"strategy":"Strat2A","used":true,"decisionType":"NEW"},{"nbUse":1,"location":{"sourceEnd":3157,"line":89,"class":"org.apache.commons.math.analysis.solvers.BisectionSolver","sourceStart":3157},"value":{"instanceType":"Primitive","value":0,"class":"class java.lang.Double"},"epsilon":0,"strategy":"Strat4 NEW","used":true,"decisionType":"NEW"}],"endDate":1476361895125,"metadata":{"seed":10,"strategy_selection":"exploration"}},{"result":{"type":"test","success":true},"startDate":1476361895125,"locations":[{"sourceEnd":3127,"executionCount":0,"line":88,"class":"org.apache.commons.math.analysis.solvers.BisectionSolver","sourceStart":3127},{"sourceEnd":3157,"executionCount":0,"line":89,"class":"org.apache.commons.math.analysis.solvers.BisectionSolver","sourceStart":3157}],"test":{"name":"testMath369","class":"org.apache.commons.math.analysis.solvers.BisectionSolverTest"},"decisions":[{"nbUse":44,"location":{"sourceEnd":3127,"line":88,"class":"org.apache.commons.math.analysis.solvers.BisectionSolver","sourceStart":3127},"value":{"instanceType":"New","class":"org.apache.commons.math.analysis.SinFunction"},"epsilon":0,"strategy":"Strat2A","used":true,"decisionType":"NEW"},{"nbUse":1,"location":{"sourceEnd":3157,"line":89,"class":"org.apache.commons.math.analysis.solvers.BisectionSolver","sourceStart":3157},"value":{"instanceType":"Primitive","value":-1,"class":"class java.lang.Double"},"epsilon":0,"strategy":"Strat4 NEW","used":true,"decisionType":"NEW"}],"endDate":1476361895136,"metadata":{"seed":10,"strategy_selection":"exploration"}},{"result":{"type":"test","success":true},"startDate":1476361895136,"locations":[{"sourceEnd":3127,"executionCount":0,"line":88,"class":"org.apache.commons.math.analysis.solvers.BisectionSolver","sourceStart":3127},{"sourceEnd":3157,"executionCount":0,"line":89,"class":"org.apache.commons.math.analysis.solvers.BisectionSolver","sourceStart":3157}],"test":{"name":"testMath369","class":"org.apache.commons.math.analysis.solvers.BisectionSolverTest"},"decisions":[{"nbUse":44,"location":{"sourceEnd":3127,"line":88,"class":"org.apache.commons.math.analysis.solvers.BisectionSolver","sourceStart":3127},"value":{"instanceType":"New","class":"org.apache.commons.math.analysis.SinFunction"},"epsilon":0,"strategy":"Strat2A","used":true,"decisionType":"NEW"},{"nbUse":1,"location":{"sourceEnd":3157,"line":89,"class":"org.apache.commons.math.analysis.solvers.BisectionSolver","sourceStart":3157},"value":{"instanceType":"Primitive","value":1,"class":"class java.lang.Double"},"epsilon":0,"strategy":"Strat4 NEW","used":true,"decisionType":"NEW"}],"endDate":1476361895147,"metadata":{"seed":10,"strategy_selection":"exploration"}},{"result":{"error":"testMath369(org.apache.commons.math.analysis.solvers.BisectionSolverTest): null\nclass java.lang.NullPointerException: null\n    at org.apache.commons.math.analysis.solvers.BisectionSolver.solve(BisectionSolver.java:97)\n    at org.apache.commons.math.analysis.solvers.BisectionSolver.solve(BisectionSolver.java:56)\n    at org.apache.commons.math.analysis.solvers.BisectionSolver.solve(BisectionSolver.java:72)\n    at org.apache.commons.math.analysis.solvers.BisectionSolverTest.testMath369(BisectionSolverTest.java:21)\n    at sun.reflect.NativeMethodAccessorImpl.invoke0(NativeMethodAccessorImpl.java:-2)\n    at sun.reflect.NativeMethodAccessorImpl.invoke(NativeMethodAccessorImpl.java:57)\n    at sun.reflect.DelegatingMethodAccessorImpl.invoke(DelegatingMethodAccessorImpl.java:43)\n    at java.lang.reflect.Method.invoke(Method.java:606)\n    at junit.framework.TestCase.runTest(TestCase.java:176)\n    at junit.framework.TestCase.runBare(TestCase.java:141)\n    at junit.framework.TestResult$1.protect(TestResult.java:122)\n    at junit.framework.TestResult.runProtected(TestResult.java:142)\n    at junit.framework.TestResult.run(TestResult.java:125)\n    at junit.framework.TestCase.run(TestCase.java:129)\n    at junit.framework.TestSuite.runTest(TestSuite.java:255)\n    at junit.framework.TestSuite.run(TestSuite.java:250)\n    at org.junit.internal.runners.JUnit38ClassRunner.run(JUnit38ClassRunner.java:84)\n    at org.junit.runner.JUnitCore.run(JUnitCore.java:160)\n    at org.junit.runner.JUnitCore.run(JUnitCore.java:138)\n    at utils.sacha.runner.main.TestRunner.run(TestRunner.java:70)\n    at fr.inria.spirals.npefix.main.all.Launcher.run(Launcher.java:252)\n    at fr.inria.spirals.npefix.AbstractEvaluation.multipleRunsProject(AbstractEvaluation.java:77)\n    at fr.inria.spirals.npefix.resi.selector.AbstractSelectorEvaluation.runProject(AbstractSelectorEvaluation.java:35)\n    at fr.inria.spirals.npefix.resi.AbstractNPEDataset.math369(AbstractNPEDataset.java:193)\n    at sun.reflect.NativeMethodAccessorImpl.invoke0(NativeMethodAccessorImpl.java:-2)\n\n\n","type":"test","success":false},"startDate":1476361895158,"test":{"name":"testMath369","class":"org.apache.commons.math.analysis.solvers.BisectionSolverTest"},"decisions":[{"nbUse":0,"location":{"sourceEnd":3127,"line":88,"class":"org.apache.commons.math.analysis.solvers.BisectionSolver","sourceStart":3127},"value":{"instanceType":"New","class":"org.apache.commons.math.analysis.SinFunction"},"epsilon":0,"strategy":"Strat2B","used":true,"decisionType":"NEW"}],"endDate":1476361895169,"metadata":{"seed":10,"strategy_selection":"exploration"}},{"result":{"type":"test","success":true},"startDate":1476361895169,"locations":[{"sourceEnd":3127,"executionCount":0,"line":88,"class":"org.apache.commons.math.analysis.solvers.BisectionSolver","sourceStart":3127},{"sourceEnd":3157,"executionCount":0,"line":89,"class":"org.apache.commons.math.analysis.solvers.BisectionSolver","sourceStart":3157}],"test":{"name":"testMath369","class":"org.apache.commons.math.analysis.solvers.BisectionSolverTest"},"decisions":[{"nbUse":44,"location":{"sourceEnd":3127,"line":88,"class":"org.apache.commons.math.analysis.solvers.BisectionSolver","sourceStart":3127},"value":{"instanceType":"Primitive","value":false,"class":"class java.lang.Boolean"},"epsilon":0,"strategy":"Strat3","used":true,"decisionType":"NEW"},{"nbUse":18,"location":{"sourceEnd":3157,"line":89,"class":"org.apache.commons.math.analysis.solvers.BisectionSolver","sourceStart":3157},"value":{"instanceType":"New","class":"org.apache.commons.math.analysis.SinFunction"},"epsilon":0,"strategy":"Strat2A","used":true,"decisionType":"NEW"}],"endDate":1476361895184,"metadata":{"seed":10,"strategy_selection":"exploration"}},{"result":{"error":"testMath369(org.apache.commons.math.analysis.solvers.BisectionSolverTest): null\nclass java.lang.NullPointerException: null\n    at org.apache.commons.math.analysis.solvers.BisectionSolver.solve(BisectionSolver.java:101)\n    at org.apache.commons.math.analysis.solvers.BisectionSolver.solve(BisectionSolver.java:56)\n    at org.apache.commons.math.analysis.solvers.BisectionSolver.solve(BisectionSolver.java:72)\n    at org.apache.commons.math.analysis.solvers.BisectionSolverTest.testMath369(BisectionSolverTest.java:21)\n    at sun.reflect.NativeMethodAccessorImpl.invoke0(NativeMethodAccessorImpl.java:-2)\n    at sun.reflect.NativeMethodAccessorImpl.invoke(NativeMethodAccessorImpl.java:57)\n    at sun.reflect.DelegatingMethodAccessorImpl.invoke(DelegatingMethodAccessorImpl.java:43)\n    at java.lang.reflect.Method.invoke(Method.java:606)\n    at junit.framework.TestCase.runTest(TestCase.java:176)\n    at junit.framework.TestCase.runBare(TestCase.java:141)\n    at junit.framework.TestResult$1.protect(TestResult.java:122)\n    at junit.framework.TestResult.runProtected(TestResult.java:142)\n    at junit.framework.TestResult.run(TestResult.java:125)\n    at junit.framework.TestCase.run(TestCase.java:129)\n    at junit.framework.TestSuite.runTest(TestSuite.java:255)\n    at junit.framework.TestSuite.run(TestSuite.java:250)\n    at org.junit.internal.runners.JUnit38ClassRunner.run(JUnit38ClassRunner.java:84)\n    at org.junit.runner.JUnitCore.run(JUnitCore.java:160)\n    at org.junit.runner.JUnitCore.run(JUnitCore.java:138)\n    at utils.sacha.runner.main.TestRunner.run(TestRunner.java:70)\n    at fr.inria.spirals.npefix.main.all.Launcher.run(Launcher.java:252)\n    at fr.inria.spirals.npefix.AbstractEvaluation.multipleRunsProject(AbstractEvaluation.java:77)\n    at fr.inria.spirals.npefix.resi.selector.AbstractSelectorEvaluation.runProject(AbstractSelectorEvaluation.java:35)\n    at fr.inria.spirals.npefix.resi.AbstractNPEDataset.math369(AbstractNPEDataset.java:193)\n    at sun.reflect.NativeMethodAccessorImpl.invoke0(NativeMethodAccessorImpl.java:-2)\n\n\n","type":"test","success":false},"startDate":1476361895184,"locations":[{"sourceEnd":3127,"executionCount":0,"line":88,"class":"org.apache.commons.math.analysis.solvers.BisectionSolver","sourceStart":3127}],"test":{"name":"testMath369","class":"org.apache.commons.math.analysis.solvers.BisectionSolverTest"},"decisions":[{"nbUse":44,"location":{"sourceEnd":3127,"line":88,"class":"org.apache.commons.math.analysis.solvers.BisectionSolver","sourceStart":3127},"value":{"instanceType":"Primitive","value":false,"class":"class java.lang.Boolean"},"epsilon":0,"strategy":"Strat3","used":true,"decisionType":"NEW"},{"nbUse":0,"location":{"sourceEnd":3157,"line":89,"class":"org.apache.commons.math.analysis.solvers.BisectionSolver","sourceStart":3157},"value":{"instanceType":"New","class":"org.apache.commons.math.analysis.SinFunction"},"epsilon":0,"strategy":"Strat2B","used":true,"decisionType":"NEW"}],"endDate":1476361895195,"metadata":{"seed":10,"strategy_selection":"exploration"}},{"result":{"type":"test","success":true},"startDate":1476361895195,"locations":[{"sourceEnd":3127,"executionCount":0,"line":88,"class":"org.apache.commons.math.analysis.solvers.BisectionSolver","sourceStart":3127},{"sourceEnd":3157,"executionCount":0,"line":89,"class":"org.apache.commons.math.analysis.solvers.BisectionSolver","sourceStart":3157}],"test":{"name":"testMath369","class":"org.apache.commons.math.analysis.solvers.BisectionSolverTest"},"decisions":[{"nbUse":44,"location":{"sourceEnd":3127,"line":88,"class":"org.apache.commons.math.analysis.solvers.BisectionSolver","sourceStart":3127},"value":{"instanceType":"Primitive","value":false,"class":"class java.lang.Boolean"},"epsilon":0,"strategy":"Strat3","used":true,"decisionType":"NEW"},{"nbUse":18,"location":{"sourceEnd":3157,"line":89,"class":"org.apache.commons.math.analysis.solvers.BisectionSolver","sourceStart":3157},"value":{"instanceType":"Primitive","value":false,"class":"class java.lang.Boolean"},"epsilon":0,"strategy":"Strat3","used":true,"decisionType":"NEW"}],"endDate":1476361895208,"metadata":{"seed":10,"strategy_selection":"exploration"}},{"result":{"type":"test","success":true},"startDate":1476361895208,"locations":[{"sourceEnd":3127,"executionCount":0,"line":88,"class":"org.apache.commons.math.analysis.solvers.BisectionSolver","sourceStart":3127},{"sourceEnd":3157,"executionCount":0,"line":89,"class":"org.apache.commons.math.analysis.solvers.BisectionSolver","sourceStart":3157}],"test":{"name":"testMath369","class":"org.apache.commons.math.analysis.solvers.BisectionSolverTest"},"decisions":[{"nbUse":44,"location":{"sourceEnd":3127,"line":88,"class":"org.apache.commons.math.analysis.solvers.BisectionSolver","sourceStart":3127},"value":{"instanceType":"Primitive","value":false,"class":"class java.lang.Boolean"},"epsilon":0,"strategy":"Strat3","used":true,"decisionType":"NEW"},{"nbUse":1,"location":{"sourceEnd":3157,"line":89,"class":"org.apache.commons.math.analysis.solvers.BisectionSolver","sourceStart":3157},"value":{"instanceType":"Variable","variableName":"min"},"epsilon":0,"strategy":"Strat4 VAR","used":true,"decisionType":"NEW"}],"endDate":1476361895219,"metadata":{"seed":10,"strategy_selection":"exploration"}},{"result":{"type":"test","success":true},"startDate":1476361895219,"locations":[{"sourceEnd":3127,"executionCount":0,"line":88,"class":"org.apache.commons.math.analysis.solvers.BisectionSolver","sourceStart":3127},{"sourceEnd":3157,"executionCount":0,"line":89,"class":"org.apache.commons.math.analysis.solvers.BisectionSolver","sourceStart":3157}],"test":{"name":"testMath369","class":"org.apache.commons.math.analysis.solvers.BisectionSolverTest"},"decisions":[{"nbUse":44,"location":{"sourceEnd":3127,"line":88,"class":"org.apache.commons.math.analysis.solvers.BisectionSolver","sourceStart":3127},"value":{"instanceType":"Primitive","value":false,"class":"class java.lang.Boolean"},"epsilon":0,"strategy":"Strat3","used":true,"decisionType":"NEW"},{"nbUse":1,"location":{"sourceEnd":3157,"line":89,"class":"org.apache.commons.math.analysis.solvers.BisectionSolver","sourceStart":3157},"value":{"instanceType":"Variable","variableName":"max"},"epsilon":0,"strategy":"Strat4 VAR","used":true,"decisionType":"NEW"}],"endDate":1476361895230,"metadata":{"seed":10,"strategy_selection":"exploration"}},{"result":{"type":"test","success":true},"startDate":1476361895230,"locations":[{"sourceEnd":3127,"executionCount":0,"line":88,"class":"org.apache.commons.math.analysis.solvers.BisectionSolver","sourceStart":3127},{"sourceEnd":3157,"executionCount":0,"line":89,"class":"org.apache.commons.math.analysis.solvers.BisectionSolver","sourceStart":3157}],"test":{"name":"testMath369","class":"org.apache.commons.math.analysis.solvers.BisectionSolverTest"},"decisions":[{"nbUse":44,"location":{"sourceEnd":3127,"line":88,"class":"org.apache.commons.math.analysis.solvers.BisectionSolver","sourceStart":3127},"value":{"instanceType":"Primitive","value":false,"class":"class java.lang.Boolean"},"epsilon":0,"strategy":"Strat3","used":true,"decisionType":"NEW"},{"nbUse":1,"location":{"sourceEnd":3157,"line":89,"class":"org.apache.commons.math.analysis.solvers.BisectionSolver","sourceStart":3157},"value":{"instanceType":"Variable","variableName":"m"},"epsilon":0,"strategy":"Strat4 VAR","used":true,"decisionType":"NEW"}],"endDate":1476361895241,"metadata":{"seed":10,"strategy_selection":"exploration"}},{"result":{"type":"test","success":true},"startDate":1476361895241,"locations":[{"sourceEnd":3127,"executionCount":0,"line":88,"class":"org.apache.commons.math.analysis.solvers.BisectionSolver","sourceStart":3127},{"sourceEnd":3157,"executionCount":0,"line":89,"class":"org.apache.commons.math.analysis.solvers.BisectionSolver","sourceStart":3157}],"test":{"name":"testMath369","class":"org.apache.commons.math.analysis.solvers.BisectionSolverTest"},"decisions":[{"nbUse":44,"location":{"sourceEnd":3127,"line":88,"class":"org.apache.commons.math.analysis.solvers.BisectionSolver","sourceStart":3127},"value":{"instanceType":"Primitive","value":false,"class":"class java.lang.Boolean"},"epsilon":0,"strategy":"Strat3","used":true,"decisionType":"NEW"},{"nbUse":1,"location":{"sourceEnd":3157,"line":89,"class":"org.apache.commons.math.analysis.solvers.BisectionSolver","sourceStart":3157},"value":{"instanceType":"Primitive","value":0,"class":"class java.lang.Double"},"epsilon":0,"strategy":"Strat4 NEW","used":true,"decisionType":"NEW"}],"endDate":1476361895252,"metadata":{"seed":10,"strategy_selection":"exploration"}},{"result":{"type":"test","success":true},"startDate":1476361895252,"locations":[{"sourceEnd":3127,"executionCount":0,"line":88,"class":"org.apache.commons.math.analysis.solvers.BisectionSolver","sourceStart":3127},{"sourceEnd":3157,"executionCount":0,"line":89,"class":"org.apache.commons.math.analysis.solvers.BisectionSolver","sourceStart":3157}],"test":{"name":"testMath369","class":"org.apache.commons.math.analysis.solvers.BisectionSolverTest"},"decisions":[{"nbUse":44,"location":{"sourceEnd":3127,"line":88,"class":"org.apache.commons.math.analysis.solvers.BisectionSolver","sourceStart":3127},"value":{"instanceType":"Primitive","value":false,"class":"class java.lang.Boolean"},"epsilon":0,"strategy":"Strat3","used":true,"decisionType":"NEW"},{"nbUse":1,"location":{"sourceEnd":3157,"line":89,"class":"org.apache.commons.math.analysis.solvers.BisectionSolver","sourceStart":3157},"value":{"instanceType":"Primitive","value":-1,"class":"class java.lang.Double"},"epsilon":0,"strategy":"Strat4 NEW","used":true,"decisionType":"NEW"}],"endDate":1476361895263,"metadata":{"seed":10,"strategy_selection":"exploration"}},{"result":{"type":"test","success":true},"startDate":1476361895263,"locations":[{"sourceEnd":3127,"executionCount":0,"line":88,"class":"org.apache.commons.math.analysis.solvers.BisectionSolver","sourceStart":3127},{"sourceEnd":3157,"executionCount":0,"line":89,"class":"org.apache.commons.math.analysis.solvers.BisectionSolver","sourceStart":3157}],"test":{"name":"testMath369","class":"org.apache.commons.math.analysis.solvers.BisectionSolverTest"},"decisions":[{"nbUse":44,"location":{"sourceEnd":3127,"line":88,"class":"org.apache.commons.math.analysis.solvers.BisectionSolver","sourceStart":3127},"value":{"instanceType":"Primitive","value":false,"class":"class java.lang.Boolean"},"epsilon":0,"strategy":"Strat3","used":true,"decisionType":"NEW"},{"nbUse":1,"location":{"sourceEnd":3157,"line":89,"class":"org.apache.commons.math.analysis.solvers.BisectionSolver","sourceStart":3157},"value":{"instanceType":"Primitive","value":1,"class":"class java.lang.Double"},"epsilon":0,"strategy":"Strat4 NEW","used":true,"decisionType":"NEW"}],"endDate":1476361895275,"metadata":{"seed":10,"strategy_selection":"exploration"}},{"result":{"type":"test","success":true},"startDate":1476361895286,"locations":[{"sourceEnd":3127,"executionCount":0,"line":88,"class":"org.apache.commons.math.analysis.solvers.BisectionSolver","sourceStart":3127}],"test":{"name":"testMath369","class":"org.apache.commons.math.analysis.solvers.BisectionSolverTest"},"decisions":[{"nbUse":1,"location":{"sourceEnd":3127,"line":88,"class":"org.apache.commons.math.analysis.solvers.BisectionSolver","sourceStart":3127},"value":{"instanceType":"Variable","variableName":"min"},"epsilon":0,"strategy":"Strat4 VAR","used":true,"decisionType":"NEW"}],"endDate":1476361895297,"metadata":{"seed":10,"strategy_selection":"exploration"}},{"result":{"type":"test","success":true},"startDate":1476361895297,"locations":[{"sourceEnd":3127,"executionCount":0,"line":88,"class":"org.apache.commons.math.analysis.solvers.BisectionSolver","sourceStart":3127}],"test":{"name":"testMath369","class":"org.apache.commons.math.analysis.solvers.BisectionSolverTest"},"decisions":[{"nbUse":1,"location":{"sourceEnd":3127,"line":88,"class":"org.apache.commons.math.analysis.solvers.BisectionSolver","sourceStart":3127},"value":{"instanceType":"Variable","variableName":"max"},"epsilon":0,"strategy":"Strat4 VAR","used":true,"decisionType":"NEW"}],"endDate":1476361895308,"metadata":{"seed":10,"strategy_selection":"exploration"}},{"result":{"type":"test","success":true},"startDate":1476361895308,"locations":[{"sourceEnd":3127,"executionCount":0,"line":88,"class":"org.apache.commons.math.analysis.solvers.BisectionSolver","sourceStart":3127}],"test":{"name":"testMath369","class":"org.apache.commons.math.analysis.solvers.BisectionSolverTest"},"decisions":[{"nbUse":1,"location":{"sourceEnd":3127,"line":88,"class":"org.apache.commons.math.analysis.solvers.BisectionSolver","sourceStart":3127},"value":{"instanceType":"Variable","variableName":"m"},"epsilon":0,"strategy":"Strat4 VAR","used":true,"decisionType":"NEW"}],"endDate":1476361895318,"metadata":{"seed":10,"strategy_selection":"exploration"}},{"result":{"type":"test","success":true},"startDate":1476361895318,"locations":[{"sourceEnd":3127,"executionCount":0,"line":88,"class":"org.apache.commons.math.analysis.solvers.BisectionSolver","sourceStart":3127}],"test":{"name":"testMath369","class":"org.apache.commons.math.analysis.solvers.BisectionSolverTest"},"decisions":[{"nbUse":1,"location":{"sourceEnd":3127,"line":88,"class":"org.apache.commons.math.analysis.solvers.BisectionSolver","sourceStart":3127},"value":{"instanceType":"Primitive","value":0,"class":"class java.lang.Double"},"epsilon":0,"strategy":"Strat4 NEW","used":true,"decisionType":"NEW"}],"endDate":1476361895329,"metadata":{"seed":10,"strategy_selection":"exploration"}},{"result":{"type":"test","success":true},"startDate":1476361895329,"locations":[{"sourceEnd":3127,"executionCount":0,"line":88,"class":"org.apache.commons.math.analysis.solvers.BisectionSolver","sourceStart":3127}],"test":{"name":"testMath369","class":"org.apache.commons.math.analysis.solvers.BisectionSolverTest"},"decisions":[{"nbUse":1,"location":{"sourceEnd":3127,"line":88,"class":"org.apache.commons.math.analysis.solvers.BisectionSolver","sourceStart":3127},"value":{"instanceType":"Primitive","value":-1,"class":"class java.lang.Double"},"epsilon":0,"strategy":"Strat4 NEW","used":true,"decisionType":"NEW"}],"endDate":1476361895340,"metadata":{"seed":10,"strategy_selection":"exploration"}},{"result":{"type":"test","success":true},"startDate":1476361895340,"locations":[{"sourceEnd":3127,"executionCount":0,"line":88,"class":"org.apache.commons.math.analysis.solvers.BisectionSolver","sourceStart":3127}],"test":{"name":"testMath369","class":"org.apache.commons.math.analysis.solvers.BisectionSolverTest"},"decisions":[{"nbUse":1,"location":{"sourceEnd":3127,"line":88,"class":"org.apache.commons.math.analysis.solvers.BisectionSolver","sourceStart":3127},"value":{"instanceType":"Primitive","value":1,"class":"class java.lang.Double"},"epsilon":0,"strategy":"Strat4 NEW","used":true,"decisionType":"NEW"}],"endDate":1476361895350,"metadata":{"seed":10,"strategy_selection":"exploration"}}],"start":1476361860151,"searchSpace":[{"nbUse":18,"location":{"sourceEnd":3157,"line":89,"class":"org.apache.commons.math.analysis.solvers.BisectionSolver","sourceStart":3157},"value":{"instanceType":"New","class":"org.apache.commons.math.analysis.SinFunction"},"epsilon":0,"strategy":"Strat2A","used":true,"decisionType":"NEW"},{"nbUse":0,"location":{"sourceEnd":3157,"line":89,"class":"org.apache.commons.math.analysis.solvers.BisectionSolver","sourceStart":3157},"value":{"instanceType":"New","class":"org.apache.commons.math.analysis.SinFunction"},"epsilon":0,"strategy":"Strat2B","used":false,"decisionType":"RANDOM"},{"nbUse":0,"location":{"sourceEnd":3157,"line":89,"class":"org.apache.commons.math.analysis.solvers.BisectionSolver","sourceStart":3157},"value":{"instanceType":"Primitive","value":false,"class":"class java.lang.Boolean"},"epsilon":0,"strategy":"Strat3","used":false,"decisionType":"RANDOM"},{"nbUse":0,"location":{"sourceEnd":3157,"line":89,"class":"org.apache.commons.math.analysis.solvers.BisectionSolver","sourceStart":3157},"value":{"instanceType":"Variable","variableName":"min"},"epsilon":0,"strategy":"Strat4 VAR","used":false,"decisionType":"RANDOM"},{"nbUse":0,"location":{"sourceEnd":3157,"line":89,"class":"org.apache.commons.math.analysis.solvers.BisectionSolver","sourceStart":3157},"value":{"instanceType":"Variable","variableName":"max"},"epsilon":0,"strategy":"Strat4 VAR","used":false,"decisionType":"RANDOM"},{"nbUse":0,"location":{"sourceEnd":3157,"line":89,"class":"org.apache.commons.math.analysis.solvers.BisectionSolver","sourceStart":3157},"value":{"instanceType":"Variable","variableName":"fmin"},"epsilon":0,"strategy":"Strat4 VAR","used":false,"decisionType":"RANDOM"},{"nbUse":0,"location":{"sourceEnd":3157,"line":89,"class":"org.apache.commons.math.analysis.solvers.BisectionSolver","sourceStart":3157},"value":{"instanceType":"Variable","variableName":"m"},"epsilon":0,"strategy":"Strat4 VAR","used":false,"decisionType":"RANDOM"},{"nbUse":0,"location":{"sourceEnd":3127,"line":88,"class":"org.apache.commons.math.analysis.solvers.BisectionSolver","sourceStart":3127},"value":{"instanceType":"Primitive","value":1,"class":"class java.lang.Double"},"epsilon":0,"strategy":"Strat4 NEW","used":false,"decisionType":"RANDOM"},{"nbUse":0,"location":{"sourceEnd":3127,"line":88,"class":"org.apache.commons.math.analysis.solvers.BisectionSolver","sourceStart":3127},"value":{"instanceType":"Primitive","value":-1,"class":"class java.lang.Double"},"epsilon":0,"strategy":"Strat4 NEW","used":false,"decisionType":"RANDOM"},{"nbUse":0,"location":{"sourceEnd":3127,"line":88,"class":"org.apache.commons.math.analysis.solvers.BisectionSolver","sourceStart":3127},"value":{"instanceType":"Primitive","value":0,"class":"class java.lang.Double"},"epsilon":0,"strategy":"Strat4 NEW","used":false,"decisionType":"RANDOM"},{"nbUse":0,"location":{"sourceEnd":3127,"line":88,"class":"org.apache.commons.math.analysis.solvers.BisectionSolver","sourceStart":3127},"value":{"instanceType":"Variable","variableName":"m"},"epsilon":0,"strategy":"Strat4 VAR","used":false,"decisionType":"RANDOM"},{"nbUse":0,"location":{"sourceEnd":3127,"line":88,"class":"org.apache.commons.math.analysis.solvers.BisectionSolver","sourceStart":3127},"value":{"instanceType":"Variable","variableName":"max"},"epsilon":0,"strategy":"Strat4 VAR","used":false,"decisionType":"RANDOM"},{"nbUse":0,"location":{"sourceEnd":3127,"line":88,"class":"org.apache.commons.math.analysis.solvers.BisectionSolver","sourceStart":3127},"value":{"instanceType":"Variable","variableName":"min"},"epsilon":0,"strategy":"Strat4 VAR","used":false,"decisionType":"RANDOM"},{"nbUse":0,"location":{"sourceEnd":3127,"line":88,"class":"org.apache.commons.math.analysis.solvers.BisectionSolver","sourceStart":3127},"value":{"instanceType":"Primitive","value":false,"class":"class java.lang.Boolean"},"epsilon":0,"strategy":"Strat3","used":false,"decisionType":"RANDOM"},{"nbUse":0,"location":{"sourceEnd":3127,"line":88,"class":"org.apache.commons.math.analysis.solvers.BisectionSolver","sourceStart":3127},"value":{"instanceType":"New","class":"org.apache.commons.math.analysis.SinFunction"},"epsilon":0,"strategy":"Strat2B","used":false,"decisionType":"RANDOM"},{"nbUse":44,"location":{"sourceEnd":3127,"line":88,"class":"org.apache.commons.math.analysis.solvers.BisectionSolver","sourceStart":3127},"value":{"instanceType":"New","class":"org.apache.commons.math.analysis.SinFunction"},"epsilon":0,"strategy":"Strat2A","used":true,"decisionType":"NEW"},{"nbUse":0,"location":{"sourceEnd":3157,"line":89,"class":"org.apache.commons.math.analysis.solvers.BisectionSolver","sourceStart":3157},"value":{"instanceType":"Primitive","value":1,"class":"class java.lang.Double"},"epsilon":0,"strategy":"Strat4 NEW","used":false,"decisionType":"RANDOM"},{"nbUse":0,"location":{"sourceEnd":3157,"line":89,"class":"org.apache.commons.math.analysis.solvers.BisectionSolver","sourceStart":3157},"value":{"instanceType":"Primitive","value":-1,"class":"class java.lang.Double"},"epsilon":0,"strategy":"Strat4 NEW","used":false,"decisionType":"RANDOM"},{"nbUse":0,"location":{"sourceEnd":3157,"line":89,"class":"org.apache.commons.math.analysis.solvers.BisectionSolver","sourceStart":3157},"value":{"instanceType":"Primitive","value":0,"class":"class java.lang.Double"},"epsilon":0,"strategy":"Strat4 NEW","used":false,"decisionType":"RANDOM"}],"end":1476361895416}